pyblade/.gitignore
pyblade/__init__.py
pyblade/backends/__init__.py
pyblade/backends/django.py
pyblade/backends/fastapi.py
pyblade/backends/flask.py
pyblade/cli/__init__.py
pyblade/cli/base.py
pyblade/cli/commands/__init__.py
pyblade/cli/commands/convert.py
pyblade/cli/commands/deploy.py
pyblade/cli/commands/docs.py
pyblade/cli/commands/example.py
pyblade/cli/commands/init.py
pyblade/cli/commands/login.py
pyblade/cli/commands/logout.py
pyblade/cli/commands/make:command.py
pyblade/cli/commands/make:component.py
pyblade/cli/commands/make:liveblade.py
pyblade/cli/commands/make:template.py
pyblade/cli/commands/serve.py
pyblade/cli/commands/tailwind:config.py
pyblade/cli/commands/upgrade.py
pyblade/cli/django_base.py
pyblade/cli/exceptions.py
pyblade/cli/main.py
pyblade/cli/stubs/bootstrap_layout.html.stub
pyblade/cli/stubs/commands/command.py.stub
pyblade/cli/stubs/component.html.stub
pyblade/cli/stubs/default_urlconf.html.stub
pyblade/cli/stubs/liveblade/component.py.stub
pyblade/cli/stubs/liveblade/inline_component.py.stub
pyblade/cli/stubs/liveblade/template.html.stub
pyblade/cli/stubs/pagination/bootstrap.html.stub
pyblade/cli/stubs/pagination/tailwind.html.stub
pyblade/cli/stubs/tailwind_layout.html.stub
pyblade/cli/stubs/template.html.stub
pyblade/cli/stubs/welcome.html.stub
pyblade/config.py
pyblade/engine/cache.py
pyblade/engine/contexts.py
pyblade/engine/directives.py
pyblade/engine/evaluator.py
pyblade/engine/exceptions.py
pyblade/engine/lexer.py
pyblade/engine/loader.py
pyblade/engine/nodes.py
pyblade/engine/parser.py
pyblade/engine/processor.py
pyblade/engine/renderer.py
pyblade/engine/template.py
pyblade/engine/templates/error.html
pyblade/engine/templates/error_prod.html
pyblade/engine/templates/welcome.html
pyblade/engine/wrappers/__init__.py
pyblade/engine/wrappers/base.py
pyblade/engine/wrappers/collection.py
pyblade/engine/wrappers/datetime.py
pyblade/engine/wrappers/number.py
pyblade/engine/wrappers/string.py
pyblade/liveblade/README.md
pyblade-0.2.0.dist-info/METADATA
pyblade-0.2.0.dist-info/WHEEL
pyblade-0.2.0.dist-info/entry_points.txt
pyblade-0.2.0.dist-info/licenses/LICENSE
pyblade-0.2.0.dist-info/RECORD
