Metadata-Version: 2.4
Name: PyBlade
Version: 0.2.0
Summary: PyBlade is a lightweight template engine for Python, initially designed for Django. Inspired by Laravel's Blade and Livewire, it simplifies dynamic template creation with developer-friendly @-based directives and component support, all while prioritizing security.
License: MIT
License-File: LICENSE
Author: AntaresMugisho
Author-email: hi@antaresmugisho.com
Requires-Python: >=3.10,<4.0
Classifier: License :: OSI Approved :: MIT License
Classifier: Programming Language :: Python :: 3
Classifier: Programming Language :: Python :: 3.10
Classifier: Programming Language :: Python :: 3.11
Classifier: Programming Language :: Python :: 3.12
Classifier: Programming Language :: Python :: 3.13
Classifier: Programming Language :: Python :: 3.14
Requires-Dist: click (>=8.1.8,<9.0.0)
Requires-Dist: colorama (>=0.4.6,<0.5.0)
Requires-Dist: questionary (>=2.0.1,<3.0.0)
Requires-Dist: rich (>=13.9.4,<14.0.0)
